<?xml version="1.0" encoding="UTF-8" ?>
<?xml-stylesheet href="http://www.gridlabd.org/gridlabd-4_0.xsl" type="text/xsl"?>
<gridlabd>
	<version.major>4</version.major>
	<version.minor>0</version.minor>
	<version.patch>0</version.patch>
	<version.build>17081</version.build>
	<version.branch>master:17081</version.branch>
	<command_line>"/Users/dchassin/bin/gridlabd.bin test_switch_coordinator.glm"</command_line>
	<environment>batch</environment>
	<quiet>FALSE</quiet>
	<warn>TRUE</warn>
	<debugger>FALSE</debugger>
	<gdb>FALSE</gdb>
	<debug>TRUE</debug>
	<test>FALSE</test>
	<verbose>TRUE</verbose>
	<iteration_limit>100</iteration_limit>
	<workdir>/Users/dchassin/gridlabd/source/gismo/autotest</workdir>
	<dumpfile>gridlabd.xml</dumpfile>
	<savefile>""</savefile>
	<dumpall>FALSE</dumpall>
	<runchecks>FALSE</runchecks>
	<threadcount>1</threadcount>
	<profiler>FALSE</profiler>
	<pauseatexit>FALSE</pauseatexit>
	<testoutputfile>test.txt</testoutputfile>
	<xml_encoding>8</xml_encoding>
	<clock>2011-01-01 00:00:10 UTC</clock>
	<starttime>2011-01-01 00:00:00 UTC</starttime>
	<stoptime>2011-01-01 00:00:15 UTC</stoptime>
	<double_format>%+lg</double_format>
	<complex_format>%+lg%+lg%c</complex_format>
	<object_format>%s:%d</object_format>
	<object_scan>%[^:]:%d</object_scan>
	<object_tree_balance>FALSE</object_tree_balance>
	<kmlfile>""</kmlfile>
	<modelname>test_switch_coordinator.glm</modelname>
	<execdir>/Users/dchassin/bin</execdir>
	<strictnames>TRUE</strictnames>
	<website>http://www.gridlabd.org/</website>
	<urlbase>http://www.gridlabd.org/</urlbase>
	<randomseed>658742374</randomseed>
	<include>""</include>
	<trace>""</trace>
	<gdb_window>FALSE</gdb_window>
	<tmp>/Users/dchassin/.gridlabd/tmp</tmp>
	<force_compile>0</force_compile>
	<nolocks>FALSE</nolocks>
	<skipsafe>FALSE</skipsafe>
	<dateformat>ISO</dateformat>
	<init_sequence>DEFERRED</init_sequence>
	<minimum_timestep>1</minimum_timestep>
	<platform>MACOSX</platform>
	<suppress_repeat_messages>FALSE</suppress_repeat_messages>
	<maximum_synctime>60</maximum_synctime>
	<run_realtime>FALSE</run_realtime>
	<enter_realtime>NEVER</enter_realtime>
	<realtime_metric>+0</realtime_metric>
	<no_deprecate>TRUE</no_deprecate>
	<streaming_io>FALSE</streaming_io>
	<compileonly>FALSE</compileonly>
	<relax_naming_rules>FALSE</relax_naming_rules>
	<browser>safari</browser>
	<server_portnum>0</server_portnum>
	<server_quit_on_close>FALSE</server_quit_on_close>
	<client_allowed>""</client_allowed>
	<autoclean>TRUE</autoclean>
	<technology_readiness_level>QUALIFIED</technology_readiness_level>
	<show_progress>TRUE</show_progress>
	<checkpoint_type>NONE</checkpoint_type>
	<checkpoint_file>""</checkpoint_file>
	<checkpoint_seqnum>0</checkpoint_seqnum>
	<checkpoint_interval>0</checkpoint_interval>
	<checkpoint_keepall>FALSE</checkpoint_keepall>
	<check_version>FALSE</check_version>
	<random_number_generator>RNG3</random_number_generator>
	<mainloop_state>INIT</mainloop_state>
	<pauseat>NEVER</pauseat>
	<infourl>http://gridlab-d.sourceforge.net/info.php?title=Special:Search/</infourl>
	<hostname>localhost</hostname>
	<hostaddr>127.0.0.1</hostaddr>
	<autostart_gui>TRUE</autostart_gui>
	<master>""</master>
	<master_port>0</master_port>
	<multirun_mode>STANDALONE</multirun_mode>
	<multirun_conn>NONE</multirun_conn>
	<signal_timeout>5000</signal_timeout>
	<slave_port>6267</slave_port>
	<slave_id>0</slave_id>
	<return_code>0</return_code>
	<exit_code>0</exit_code>
	<module_compiler_flags>NONE</module_compiler_flags>
	<init_max_defer>64</init_max_defer>
	<mt_analysis>FALSE</mt_analysis>
	<inline_block_size>1048576</inline_block_size>
	<validate>TSTD|RALL</validate>
	<sanitize>NAMES|POSITIONS</sanitize>
	<sanitize_prefix>GLD_</sanitize_prefix>
	<sanitize_index>.txt</sanitize_index>
	<sanitize_offset>""</sanitize_offset>
	<simulation_mode>EVENT</simulation_mode>
	<deltamode_timestep>10000000</deltamode_timestep>
	<deltamode_maximumtime>3600000000000</deltamode_maximumtime>
	<deltaclock>0</deltaclock>
	<delta_current_clock>+0</delta_current_clock>
	<deltamode_updateorder>powerflow,tape</deltamode_updateorder>
	<deltamode_iteration_limit>10</deltamode_iteration_limit>
	<run_powerworld>FALSE</run_powerworld>
	<bigranks>TRUE</bigranks>
	<exename>/Users/dchassin/bin/gridlabd.bin</exename>
	<wget_options>"maxsize:100MB;update:newer"</wget_options>
	<svnroot>http://gridlab-d.svn.sourceforge.net/svnroot/gridlab-d</svnroot>
	<allow_reinclude>FALSE</allow_reinclude>
	<SEQ_LOAD>4</SEQ_LOAD>
	<SEQ_SWITCH>4</SEQ_SWITCH>
	<timezone>UTC0</timezone>
	<sync-order>
		<pass>
			<name>pretopdown</name>
			<rank>
				<ordinal>7</ordinal>
				<object>
					<name>swing</name>
					<id>0</id>
				</object>
			</rank>
			<rank>
				<ordinal>5</ordinal>
				<object>
					<name>load_1</name>
					<id>1</id>
				</object>
				<object>
					<name>load_2</name>
					<id>2</id>
				</object>
				<object>
					<name>load_4</name>
					<id>4</id>
				</object>
				<object>
					<name>load_3</name>
					<id>3</id>
				</object>
			</rank>
			<rank>
				<ordinal>1</ordinal>
				<object>
					<name>switch_4</name>
					<id>11</id>
				</object>
				<object>
					<name>switch_3</name>
					<id>9</id>
				</object>
				<object>
					<name>switch_1</name>
					<id>5</id>
				</object>
				<object>
					<name>switch_2</name>
					<id>7</id>
				</object>
			</rank>
			<rank>
				<ordinal>0</ordinal>
				<object>
					<name>(player:15)</name>
					<id>15</id>
				</object>
				<object>
					<name>(player:14)</name>
					<id>14</id>
				</object>
			</rank>
		</pass>
		<pass>
			<name>bottomup</name>
			<rank>
				<ordinal>1</ordinal>
				<object>
					<name>switch_2</name>
					<id>7</id>
				</object>
				<object>
					<name>switch_1</name>
					<id>5</id>
				</object>
				<object>
					<name>controller_1</name>
					<id>13</id>
				</object>
				<object>
					<name>switch_3</name>
					<id>9</id>
				</object>
				<object>
					<name>switch_4</name>
					<id>11</id>
				</object>
			</rank>
			<rank>
				<ordinal>5</ordinal>
				<object>
					<name>load_2</name>
					<id>2</id>
				</object>
				<object>
					<name>load_3</name>
					<id>3</id>
				</object>
				<object>
					<name>load_1</name>
					<id>1</id>
				</object>
				<object>
					<name>load_4</name>
					<id>4</id>
				</object>
			</rank>
			<rank>
				<ordinal>7</ordinal>
				<object>
					<name>swing</name>
					<id>0</id>
				</object>
			</rank>
		</pass>
		<pass>
			<name>posttopdown</name>
			<rank>
				<ordinal>7</ordinal>
				<object>
					<name>swing</name>
					<id>0</id>
				</object>
			</rank>
			<rank>
				<ordinal>5</ordinal>
				<object>
					<name>load_1</name>
					<id>1</id>
				</object>
				<object>
					<name>load_3</name>
					<id>3</id>
				</object>
				<object>
					<name>load_2</name>
					<id>2</id>
				</object>
				<object>
					<name>load_4</name>
					<id>4</id>
				</object>
			</rank>
			<rank>
				<ordinal>1</ordinal>
				<object>
					<name>switch_1</name>
					<id>5</id>
				</object>
				<object>
					<name>switch_2</name>
					<id>7</id>
				</object>
				<object>
					<name>switch_3</name>
					<id>9</id>
				</object>
				<object>
					<name>switch_4</name>
					<id>11</id>
				</object>
			</rank>
			<rank>
				<ordinal>0</ordinal>
				<object>
					<name>(recorder:10)</name>
					<id>10</id>
				</object>
				<object>
					<name>(recorder:12)</name>
					<id>12</id>
				</object>
				<object>
					<name>(recorder:8)</name>
					<id>8</id>
				</object>
				<object>
					<name>(recorder:6)</name>
					<id>6</id>
				</object>
				<object>
					<name>(recorder:16)</name>
					<id>16</id>
				</object>
			</rank>
		</pass>
	</sync-order>
	<powerflow>
		<version.major>4</version.major>
		<version.minor>0</version.minor>
		<node_list>
			<inherits_from>powerflow_object</inherits_from>
		</node_list>
		<link_list>
			<inherits_from>powerflow_object</inherits_from>
		</link_list>
		<capacitor_list>
			<inherits_from>node</inherits_from>
		</capacitor_list>
		<fuse_list>
			<inherits_from>link</inherits_from>
		</fuse_list>
		<meter_list>
			<inherits_from>node</inherits_from>
			<meter>
				<id>0</id>
				<rank>7</rank>
				<out_svc>NEVER</out_svc>
				<clock>2011-01-01 00:00:08 UTC</clock>
				<name>swing</name>
				<measured_real_energy>+1.16913e-08 Wh</measured_real_energy>
				<measured_reactive_energy>-7.91416e-08 VAh</measured_reactive_energy>
				<measured_power>-6.91916e-06+2.58227e-05i VA</measured_power>
				<measured_power_A>+0+0i VA</measured_power_A>
				<measured_power_B>+3.08693e-05+75d VA</measured_power_B>
				<measured_power_C>+1.54346e-05-165d VA</measured_power_C>
				<measured_demand>+3.7807e-05 W</measured_demand>
				<measured_real_power>-6.91916e-06 W</measured_real_power>
				<measured_reactive_power>+2.58227e-05 VAr</measured_reactive_power>
				<meter_power_consumption>+0+0j VA</meter_power_consumption>
				<measured_voltage_A>+2400+0d V</measured_voltage_A>
				<measured_voltage_B>+2400+120d V</measured_voltage_B>
				<measured_voltage_C>+2400-120d V</measured_voltage_C>
				<measured_voltage_AB>+4156.92-30d V</measured_voltage_AB>
				<measured_voltage_BC>+4156.92+90d V</measured_voltage_BC>
				<measured_voltage_CA>+4156.92-150d V</measured_voltage_CA>
				<measured_current_A>+0+0j A</measured_current_A>
				<measured_current_B>+9.09495e-09+9.09495e-09j A</measured_current_B>
				<measured_current_C>+4.54747e-09+4.54747e-09j A</measured_current_C>
				<customer_interrupted>FALSE</customer_interrupted>
				<customer_interrupted_secondary>FALSE</customer_interrupted_secondary>
				<monthly_bill>+0 $</monthly_bill>
				<previous_monthly_bill>+0 $</previous_monthly_bill>
				<previous_monthly_energy>+0 kWh</previous_monthly_energy>
				<monthly_fee>+0 $</monthly_fee>
				<monthly_energy>+0 kWh</monthly_energy>
				<bill_mode>NONE</bill_mode>
				<bill_day>15</bill_day>
				<price>+0 $/kWh</price>
				<price_base>+0 $/kWh</price_base>
				<first_tier_price>+0 $/kWh</first_tier_price>
				<first_tier_energy>+0 kWh</first_tier_energy>
				<second_tier_price>+0 $/kWh</second_tier_price>
				<second_tier_energy>+0 kWh</second_tier_energy>
				<third_tier_price>+0 $/kWh</third_tier_price>
				<third_tier_energy>+0 kWh</third_tier_energy>
				<bustype>SWING</bustype>
				<busflags>HASSOURCE</busflags>
				<maximum_voltage_error>+0.0024 V</maximum_voltage_error>
				<voltage_A>+2400+0d V</voltage_A>
				<voltage_B>+2400+120d V</voltage_B>
				<voltage_C>+2400-120d V</voltage_C>
				<voltage_AB>+4156.92-30d V</voltage_AB>
				<voltage_BC>+4156.92+90d V</voltage_BC>
				<voltage_CA>+4156.92-150d V</voltage_CA>
				<current_A>+0+0i A</current_A>
				<current_B>+0+0i A</current_B>
				<current_C>+0+0i A</current_C>
				<power_A>+0+0i VA</power_A>
				<power_B>+0+0i VA</power_B>
				<power_C>+0+0i VA</power_C>
				<shunt_A>+0+0i S</shunt_A>
				<shunt_B>+0+0i S</shunt_B>
				<shunt_C>+0+0i S</shunt_C>
				<prerotated_current_A>+0+0i A</prerotated_current_A>
				<prerotated_current_B>+0+0i A</prerotated_current_B>
				<prerotated_current_C>+0+0i A</prerotated_current_C>
				<current_AB>+0+0j A</current_AB>
				<current_BC>+0+0j A</current_BC>
				<current_CA>+0+0j A</current_CA>
				<current_AN>+0+0j A</current_AN>
				<current_BN>+0+0j A</current_BN>
				<current_CN>+0+0j A</current_CN>
				<power_AB>+0+0j VA</power_AB>
				<power_BC>+0+0j VA</power_BC>
				<power_CA>+0+0j VA</power_CA>
				<power_AN>+0+0j VA</power_AN>
				<power_BN>+0+0j VA</power_BN>
				<power_CN>+0+0j VA</power_CN>
				<shunt_AB>+0+0j S</shunt_AB>
				<shunt_BC>+0+0j S</shunt_BC>
				<shunt_CA>+0+0j S</shunt_CA>
				<shunt_AN>+0+0j S</shunt_AN>
				<shunt_BN>+0+0j S</shunt_BN>
				<shunt_CN>+0+0j S</shunt_CN>
				<mean_repair_time>+0 s</mean_repair_time>
				<frequency_measure_type>NONE</frequency_measure_type>
				<sfm_T>+0.01 s</sfm_T>
				<pll_Kp>+10 pu</pll_Kp>
				<pll_Ki>+100 pu</pll_Ki>
				<measured_angle_A>+0 rad</measured_angle_A>
				<measured_frequency_A>+60 Hz</measured_frequency_A>
				<measured_angle_B>+0 rad</measured_angle_B>
				<measured_frequency_B>+60 Hz</measured_frequency_B>
				<measured_angle_C>+0 rad</measured_angle_C>
				<measured_frequency_C>+60 Hz</measured_frequency_C>
				<measured_frequency>+60 Hz</measured_frequency>
				<service_status>IN_SERVICE</service_status>
				<service_status_double>-1</service_status_double>
				<previous_uptime>-1 min</previous_uptime>
				<current_uptime>+0.166667 min</current_uptime>
				<Norton_dynamic>FALSE</Norton_dynamic>
				<GFA_enable>FALSE</GFA_enable>
				<GFA_freq_low_trip>+59.5 Hz</GFA_freq_low_trip>
				<GFA_freq_high_trip>+60.5 Hz</GFA_freq_high_trip>
				<GFA_volt_low_trip>+0.8 pu</GFA_volt_low_trip>
				<GFA_volt_high_trip>+1.2 pu</GFA_volt_high_trip>
				<GFA_reconnect_time>+300 s</GFA_reconnect_time>
				<GFA_freq_disconnect_time>+0.2 s</GFA_freq_disconnect_time>
				<GFA_volt_disconnect_time>+0.2 s</GFA_volt_disconnect_time>
				<GFA_status>TRUE</GFA_status>
				<phases>ABC</phases>
				<nominal_voltage>+2400 V</nominal_voltage>
			</meter>
			<meter>
				<id>1</id>
				<rank>5</rank>
				<out_svc>NEVER</out_svc>
				<parent>swing</parent>
				<clock>2011-01-01 00:00:08 UTC</clock>
				<name>load_1</name>
				<measured_real_energy>+0 Wh</measured_real_energy>
				<measured_reactive_energy>+0 VAh</measured_reactive_energy>
				<measured_power>+0+0d VA</measured_power>
				<measured_power_A>+0+0d VA</measured_power_A>
				<measured_power_B>+0+0d VA</measured_power_B>
				<measured_power_C>+0+0d VA</measured_power_C>
				<measured_demand>+0 W</measured_demand>
				<measured_real_power>+0 W</measured_real_power>
				<measured_reactive_power>+0 VAr</measured_reactive_power>
				<meter_power_consumption>+0+0j VA</meter_power_consumption>
				<measured_voltage_A>+2400+0d V</measured_voltage_A>
				<measured_voltage_B>+2400+120d V</measured_voltage_B>
				<measured_voltage_C>+2400-120d V</measured_voltage_C>
				<measured_voltage_AB>+4156.92-30d V</measured_voltage_AB>
				<measured_voltage_BC>+4156.92+90d V</measured_voltage_BC>
				<measured_voltage_CA>+4156.92-150d V</measured_voltage_CA>
				<measured_current_A>+0+0j A</measured_current_A>
				<measured_current_B>+0+0j A</measured_current_B>
				<measured_current_C>+0+0j A</measured_current_C>
				<customer_interrupted>FALSE</customer_interrupted>
				<customer_interrupted_secondary>FALSE</customer_interrupted_secondary>
				<monthly_bill>+0 $</monthly_bill>
				<previous_monthly_bill>+0 $</previous_monthly_bill>
				<previous_monthly_energy>+0 kWh</previous_monthly_energy>
				<monthly_fee>+0 $</monthly_fee>
				<monthly_energy>+0 kWh</monthly_energy>
				<bill_mode>NONE</bill_mode>
				<bill_day>15</bill_day>
				<price>+0 $/kWh</price>
				<price_base>+0 $/kWh</price_base>
				<first_tier_price>+0 $/kWh</first_tier_price>
				<first_tier_energy>+0 kWh</first_tier_energy>
				<second_tier_price>+0 $/kWh</second_tier_price>
				<second_tier_energy>+0 kWh</second_tier_energy>
				<third_tier_price>+0 $/kWh</third_tier_price>
				<third_tier_energy>+0 kWh</third_tier_energy>
				<bustype>PQ</bustype>
				<busflags>HASSOURCE</busflags>
				<maximum_voltage_error>+0.0024 V</maximum_voltage_error>
				<voltage_A>+2400+0d V</voltage_A>
				<voltage_B>+2400+120d V</voltage_B>
				<voltage_C>+2400-120d V</voltage_C>
				<voltage_AB>+4156.92-30d V</voltage_AB>
				<voltage_BC>+4156.92+90d V</voltage_BC>
				<voltage_CA>+4156.92-150d V</voltage_CA>
				<current_A>+0+0i A</current_A>
				<current_B>+0+0i A</current_B>
				<current_C>+0+0i A</current_C>
				<power_A>+0+0i VA</power_A>
				<power_B>+0+0i VA</power_B>
				<power_C>+0+0i VA</power_C>
				<shunt_A>+0+0i S</shunt_A>
				<shunt_B>+0+0i S</shunt_B>
				<shunt_C>+0+0i S</shunt_C>
				<prerotated_current_A>+0+0i A</prerotated_current_A>
				<prerotated_current_B>+0+0i A</prerotated_current_B>
				<prerotated_current_C>+0+0i A</prerotated_current_C>
				<current_AB>+0+0j A</current_AB>
				<current_BC>+0+0j A</current_BC>
				<current_CA>+0+0j A</current_CA>
				<current_AN>+0+0j A</current_AN>
				<current_BN>+0+0j A</current_BN>
				<current_CN>+0+0j A</current_CN>
				<power_AB>+0+0j VA</power_AB>
				<power_BC>+0+0j VA</power_BC>
				<power_CA>+0+0j VA</power_CA>
				<power_AN>+0+0j VA</power_AN>
				<power_BN>+0+0j VA</power_BN>
				<power_CN>+0+0j VA</power_CN>
				<shunt_AB>+0+0j S</shunt_AB>
				<shunt_BC>+0+0j S</shunt_BC>
				<shunt_CA>+0+0j S</shunt_CA>
				<shunt_AN>+0+0j S</shunt_AN>
				<shunt_BN>+0+0j S</shunt_BN>
				<shunt_CN>+0+0j S</shunt_CN>
				<mean_repair_time>+0 s</mean_repair_time>
				<frequency_measure_type>NONE</frequency_measure_type>
				<sfm_T>+0.01 s</sfm_T>
				<pll_Kp>+10 pu</pll_Kp>
				<pll_Ki>+100 pu</pll_Ki>
				<measured_angle_A>+0 rad</measured_angle_A>
				<measured_frequency_A>+60 Hz</measured_frequency_A>
				<measured_angle_B>+0 rad</measured_angle_B>
				<measured_frequency_B>+60 Hz</measured_frequency_B>
				<measured_angle_C>+0 rad</measured_angle_C>
				<measured_frequency_C>+60 Hz</measured_frequency_C>
				<measured_frequency>+60 Hz</measured_frequency>
				<service_status>IN_SERVICE</service_status>
				<service_status_double>-1</service_status_double>
				<previous_uptime>-1 min</previous_uptime>
				<current_uptime>+0.166667 min</current_uptime>
				<Norton_dynamic>FALSE</Norton_dynamic>
				<GFA_enable>FALSE</GFA_enable>
				<GFA_freq_low_trip>+59.5 Hz</GFA_freq_low_trip>
				<GFA_freq_high_trip>+60.5 Hz</GFA_freq_high_trip>
				<GFA_volt_low_trip>+0.8 pu</GFA_volt_low_trip>
				<GFA_volt_high_trip>+1.2 pu</GFA_volt_high_trip>
				<GFA_reconnect_time>+300 s</GFA_reconnect_time>
				<GFA_freq_disconnect_time>+0.2 s</GFA_freq_disconnect_time>
				<GFA_volt_disconnect_time>+0.2 s</GFA_volt_disconnect_time>
				<GFA_status>TRUE</GFA_status>
				<phases>ABCN</phases>
				<nominal_voltage>+2400 V</nominal_voltage>
			</meter>
			<meter>
				<id>2</id>
				<rank>5</rank>
				<out_svc>NEVER</out_svc>
				<parent>swing</parent>
				<clock>2011-01-01 00:00:08 UTC</clock>
				<name>load_2</name>
				<measured_real_energy>+0 Wh</measured_real_energy>
				<measured_reactive_energy>+0 VAh</measured_reactive_energy>
				<measured_power>+0+0d VA</measured_power>
				<measured_power_A>+0+0d VA</measured_power_A>
				<measured_power_B>+0+0d VA</measured_power_B>
				<measured_power_C>+0+0d VA</measured_power_C>
				<measured_demand>+0 W</measured_demand>
				<measured_real_power>+0 W</measured_real_power>
				<measured_reactive_power>+0 VAr</measured_reactive_power>
				<meter_power_consumption>+0+0j VA</meter_power_consumption>
				<measured_voltage_A>+2400+0d V</measured_voltage_A>
				<measured_voltage_B>+2400+120d V</measured_voltage_B>
				<measured_voltage_C>+2400-120d V</measured_voltage_C>
				<measured_voltage_AB>+4156.92-30d V</measured_voltage_AB>
				<measured_voltage_BC>+4156.92+90d V</measured_voltage_BC>
				<measured_voltage_CA>+4156.92-150d V</measured_voltage_CA>
				<measured_current_A>+0+0j A</measured_current_A>
				<measured_current_B>+0+0j A</measured_current_B>
				<measured_current_C>+0+0j A</measured_current_C>
				<customer_interrupted>FALSE</customer_interrupted>
				<customer_interrupted_secondary>FALSE</customer_interrupted_secondary>
				<monthly_bill>+0 $</monthly_bill>
				<previous_monthly_bill>+0 $</previous_monthly_bill>
				<previous_monthly_energy>+0 kWh</previous_monthly_energy>
				<monthly_fee>+0 $</monthly_fee>
				<monthly_energy>+0 kWh</monthly_energy>
				<bill_mode>NONE</bill_mode>
				<bill_day>15</bill_day>
				<price>+0 $/kWh</price>
				<price_base>+0 $/kWh</price_base>
				<first_tier_price>+0 $/kWh</first_tier_price>
				<first_tier_energy>+0 kWh</first_tier_energy>
				<second_tier_price>+0 $/kWh</second_tier_price>
				<second_tier_energy>+0 kWh</second_tier_energy>
				<third_tier_price>+0 $/kWh</third_tier_price>
				<third_tier_energy>+0 kWh</third_tier_energy>
				<bustype>PQ</bustype>
				<busflags>HASSOURCE</busflags>
				<maximum_voltage_error>+0.0024 V</maximum_voltage_error>
				<voltage_A>+2400+0d V</voltage_A>
				<voltage_B>+2400+120d V</voltage_B>
				<voltage_C>+2400-120d V</voltage_C>
				<voltage_AB>+4156.92-30d V</voltage_AB>
				<voltage_BC>+4156.92+90d V</voltage_BC>
				<voltage_CA>+4156.92-150d V</voltage_CA>
				<current_A>+0+0i A</current_A>
				<current_B>+0+0i A</current_B>
				<current_C>+0+0i A</current_C>
				<power_A>+0+0i VA</power_A>
				<power_B>+0+0i VA</power_B>
				<power_C>+0+0i VA</power_C>
				<shunt_A>+0+0i S</shunt_A>
				<shunt_B>+0+0i S</shunt_B>
				<shunt_C>+0+0i S</shunt_C>
				<prerotated_current_A>+0+0i A</prerotated_current_A>
				<prerotated_current_B>+0+0i A</prerotated_current_B>
				<prerotated_current_C>+0+0i A</prerotated_current_C>
				<current_AB>+0+0j A</current_AB>
				<current_BC>+0+0j A</current_BC>
				<current_CA>+0+0j A</current_CA>
				<current_AN>+0+0j A</current_AN>
				<current_BN>+0+0j A</current_BN>
				<current_CN>+0+0j A</current_CN>
				<power_AB>+0+0j VA</power_AB>
				<power_BC>+0+0j VA</power_BC>
				<power_CA>+0+0j VA</power_CA>
				<power_AN>+0+0j VA</power_AN>
				<power_BN>+0+0j VA</power_BN>
				<power_CN>+0+0j VA</power_CN>
				<shunt_AB>+0+0j S</shunt_AB>
				<shunt_BC>+0+0j S</shunt_BC>
				<shunt_CA>+0+0j S</shunt_CA>
				<shunt_AN>+0+0j S</shunt_AN>
				<shunt_BN>+0+0j S</shunt_BN>
				<shunt_CN>+0+0j S</shunt_CN>
				<mean_repair_time>+0 s</mean_repair_time>
				<frequency_measure_type>NONE</frequency_measure_type>
				<sfm_T>+0.01 s</sfm_T>
				<pll_Kp>+10 pu</pll_Kp>
				<pll_Ki>+100 pu</pll_Ki>
				<measured_angle_A>+0 rad</measured_angle_A>
				<measured_frequency_A>+60 Hz</measured_frequency_A>
				<measured_angle_B>+0 rad</measured_angle_B>
				<measured_frequency_B>+60 Hz</measured_frequency_B>
				<measured_angle_C>+0 rad</measured_angle_C>
				<measured_frequency_C>+60 Hz</measured_frequency_C>
				<measured_frequency>+60 Hz</measured_frequency>
				<service_status>IN_SERVICE</service_status>
				<service_status_double>-1</service_status_double>
				<previous_uptime>-1 min</previous_uptime>
				<current_uptime>+0.166667 min</current_uptime>
				<Norton_dynamic>FALSE</Norton_dynamic>
				<GFA_enable>FALSE</GFA_enable>
				<GFA_freq_low_trip>+59.5 Hz</GFA_freq_low_trip>
				<GFA_freq_high_trip>+60.5 Hz</GFA_freq_high_trip>
				<GFA_volt_low_trip>+0.8 pu</GFA_volt_low_trip>
				<GFA_volt_high_trip>+1.2 pu</GFA_volt_high_trip>
				<GFA_reconnect_time>+300 s</GFA_reconnect_time>
				<GFA_freq_disconnect_time>+0.2 s</GFA_freq_disconnect_time>
				<GFA_volt_disconnect_time>+0.2 s</GFA_volt_disconnect_time>
				<GFA_status>TRUE</GFA_status>
				<phases>ABCN</phases>
				<nominal_voltage>+2400 V</nominal_voltage>
			</meter>
			<meter>
				<id>3</id>
				<rank>5</rank>
				<out_svc>NEVER</out_svc>
				<parent>swing</parent>
				<clock>2011-01-01 00:00:08 UTC</clock>
				<name>load_3</name>
				<measured_real_energy>+0 Wh</measured_real_energy>
				<measured_reactive_energy>+0 VAh</measured_reactive_energy>
				<measured_power>+0+0d VA</measured_power>
				<measured_power_A>+0+0d VA</measured_power_A>
				<measured_power_B>+0+0d VA</measured_power_B>
				<measured_power_C>+0+0d VA</measured_power_C>
				<measured_demand>+0 W</measured_demand>
				<measured_real_power>+0 W</measured_real_power>
				<measured_reactive_power>+0 VAr</measured_reactive_power>
				<meter_power_consumption>+0+0j VA</meter_power_consumption>
				<measured_voltage_A>+2400+0d V</measured_voltage_A>
				<measured_voltage_B>+2400+120d V</measured_voltage_B>
				<measured_voltage_C>+2400-120d V</measured_voltage_C>
				<measured_voltage_AB>+4156.92-30d V</measured_voltage_AB>
				<measured_voltage_BC>+4156.92+90d V</measured_voltage_BC>
				<measured_voltage_CA>+4156.92-150d V</measured_voltage_CA>
				<measured_current_A>+0+0j A</measured_current_A>
				<measured_current_B>+0+0j A</measured_current_B>
				<measured_current_C>+0+0j A</measured_current_C>
				<customer_interrupted>FALSE</customer_interrupted>
				<customer_interrupted_secondary>FALSE</customer_interrupted_secondary>
				<monthly_bill>+0 $</monthly_bill>
				<previous_monthly_bill>+0 $</previous_monthly_bill>
				<previous_monthly_energy>+0 kWh</previous_monthly_energy>
				<monthly_fee>+0 $</monthly_fee>
				<monthly_energy>+0 kWh</monthly_energy>
				<bill_mode>NONE</bill_mode>
				<bill_day>15</bill_day>
				<price>+0 $/kWh</price>
				<price_base>+0 $/kWh</price_base>
				<first_tier_price>+0 $/kWh</first_tier_price>
				<first_tier_energy>+0 kWh</first_tier_energy>
				<second_tier_price>+0 $/kWh</second_tier_price>
				<second_tier_energy>+0 kWh</second_tier_energy>
				<third_tier_price>+0 $/kWh</third_tier_price>
				<third_tier_energy>+0 kWh</third_tier_energy>
				<bustype>PQ</bustype>
				<busflags>HASSOURCE</busflags>
				<maximum_voltage_error>+0.0024 V</maximum_voltage_error>
				<voltage_A>+2400+0d V</voltage_A>
				<voltage_B>+2400+120d V</voltage_B>
				<voltage_C>+2400-120d V</voltage_C>
				<voltage_AB>+4156.92-30d V</voltage_AB>
				<voltage_BC>+4156.92+90d V</voltage_BC>
				<voltage_CA>+4156.92-150d V</voltage_CA>
				<current_A>+0+0i A</current_A>
				<current_B>+0+0i A</current_B>
				<current_C>+0+0i A</current_C>
				<power_A>+0+0i VA</power_A>
				<power_B>+0+0i VA</power_B>
				<power_C>+0+0i VA</power_C>
				<shunt_A>+0+0i S</shunt_A>
				<shunt_B>+0+0i S</shunt_B>
				<shunt_C>+0+0i S</shunt_C>
				<prerotated_current_A>+0+0i A</prerotated_current_A>
				<prerotated_current_B>+0+0i A</prerotated_current_B>
				<prerotated_current_C>+0+0i A</prerotated_current_C>
				<current_AB>+0+0j A</current_AB>
				<current_BC>+0+0j A</current_BC>
				<current_CA>+0+0j A</current_CA>
				<current_AN>+0+0j A</current_AN>
				<current_BN>+0+0j A</current_BN>
				<current_CN>+0+0j A</current_CN>
				<power_AB>+0+0j VA</power_AB>
				<power_BC>+0+0j VA</power_BC>
				<power_CA>+0+0j VA</power_CA>
				<power_AN>+0+0j VA</power_AN>
				<power_BN>+0+0j VA</power_BN>
				<power_CN>+0+0j VA</power_CN>
				<shunt_AB>+0+0j S</shunt_AB>
				<shunt_BC>+0+0j S</shunt_BC>
				<shunt_CA>+0+0j S</shunt_CA>
				<shunt_AN>+0+0j S</shunt_AN>
				<shunt_BN>+0+0j S</shunt_BN>
				<shunt_CN>+0+0j S</shunt_CN>
				<mean_repair_time>+0 s</mean_repair_time>
				<frequency_measure_type>NONE</frequency_measure_type>
				<sfm_T>+0.01 s</sfm_T>
				<pll_Kp>+10 pu</pll_Kp>
				<pll_Ki>+100 pu</pll_Ki>
				<measured_angle_A>+0 rad</measured_angle_A>
				<measured_frequency_A>+60 Hz</measured_frequency_A>
				<measured_angle_B>+0 rad</measured_angle_B>
				<measured_frequency_B>+60 Hz</measured_frequency_B>
				<measured_angle_C>+0 rad</measured_angle_C>
				<measured_frequency_C>+60 Hz</measured_frequency_C>
				<measured_frequency>+60 Hz</measured_frequency>
				<service_status>IN_SERVICE</service_status>
				<service_status_double>-1</service_status_double>
				<previous_uptime>-1 min</previous_uptime>
				<current_uptime>+0.166667 min</current_uptime>
				<Norton_dynamic>FALSE</Norton_dynamic>
				<GFA_enable>FALSE</GFA_enable>
				<GFA_freq_low_trip>+59.5 Hz</GFA_freq_low_trip>
				<GFA_freq_high_trip>+60.5 Hz</GFA_freq_high_trip>
				<GFA_volt_low_trip>+0.8 pu</GFA_volt_low_trip>
				<GFA_volt_high_trip>+1.2 pu</GFA_volt_high_trip>
				<GFA_reconnect_time>+300 s</GFA_reconnect_time>
				<GFA_freq_disconnect_time>+0.2 s</GFA_freq_disconnect_time>
				<GFA_volt_disconnect_time>+0.2 s</GFA_volt_disconnect_time>
				<GFA_status>TRUE</GFA_status>
				<phases>ABCN</phases>
				<nominal_voltage>+2400 V</nominal_voltage>
			</meter>
			<meter>
				<id>4</id>
				<rank>5</rank>
				<out_svc>NEVER</out_svc>
				<parent>swing</parent>
				<clock>2011-01-01 00:00:08 UTC</clock>
				<name>load_4</name>
				<measured_real_energy>+0 Wh</measured_real_energy>
				<measured_reactive_energy>+0 VAh</measured_reactive_energy>
				<measured_power>+0+0d VA</measured_power>
				<measured_power_A>+0+0d VA</measured_power_A>
				<measured_power_B>+0+0d VA</measured_power_B>
				<measured_power_C>+0+0d VA</measured_power_C>
				<measured_demand>+0 W</measured_demand>
				<measured_real_power>+0 W</measured_real_power>
				<measured_reactive_power>+0 VAr</measured_reactive_power>
				<meter_power_consumption>+0+0j VA</meter_power_consumption>
				<measured_voltage_A>+2400+0d V</measured_voltage_A>
				<measured_voltage_B>+2400+120d V</measured_voltage_B>
				<measured_voltage_C>+2400-120d V</measured_voltage_C>
				<measured_voltage_AB>+4156.92-30d V</measured_voltage_AB>
				<measured_voltage_BC>+4156.92+90d V</measured_voltage_BC>
				<measured_voltage_CA>+4156.92-150d V</measured_voltage_CA>
				<measured_current_A>+0+0j A</measured_current_A>
				<measured_current_B>+0+0j A</measured_current_B>
				<measured_current_C>+0+0j A</measured_current_C>
				<customer_interrupted>FALSE</customer_interrupted>
				<customer_interrupted_secondary>FALSE</customer_interrupted_secondary>
				<monthly_bill>+0 $</monthly_bill>
				<previous_monthly_bill>+0 $</previous_monthly_bill>
				<previous_monthly_energy>+0 kWh</previous_monthly_energy>
				<monthly_fee>+0 $</monthly_fee>
				<monthly_energy>+0 kWh</monthly_energy>
				<bill_mode>NONE</bill_mode>
				<bill_day>15</bill_day>
				<price>+0 $/kWh</price>
				<price_base>+0 $/kWh</price_base>
				<first_tier_price>+0 $/kWh</first_tier_price>
				<first_tier_energy>+0 kWh</first_tier_energy>
				<second_tier_price>+0 $/kWh</second_tier_price>
				<second_tier_energy>+0 kWh</second_tier_energy>
				<third_tier_price>+0 $/kWh</third_tier_price>
				<third_tier_energy>+0 kWh</third_tier_energy>
				<bustype>PQ</bustype>
				<busflags>HASSOURCE</busflags>
				<maximum_voltage_error>+0.0024 V</maximum_voltage_error>
				<voltage_A>+2400+0d V</voltage_A>
				<voltage_B>+2400+120d V</voltage_B>
				<voltage_C>+2400-120d V</voltage_C>
				<voltage_AB>+4156.92-30d V</voltage_AB>
				<voltage_BC>+4156.92+90d V</voltage_BC>
				<voltage_CA>+4156.92-150d V</voltage_CA>
				<current_A>+0+0i A</current_A>
				<current_B>+0+0i A</current_B>
				<current_C>+0+0i A</current_C>
				<power_A>+0+0i VA</power_A>
				<power_B>+0+0i VA</power_B>
				<power_C>+0+0i VA</power_C>
				<shunt_A>+0+0i S</shunt_A>
				<shunt_B>+0+0i S</shunt_B>
				<shunt_C>+0+0i S</shunt_C>
				<prerotated_current_A>+0+0i A</prerotated_current_A>
				<prerotated_current_B>+0+0i A</prerotated_current_B>
				<prerotated_current_C>+0+0i A</prerotated_current_C>
				<current_AB>+0+0j A</current_AB>
				<current_BC>+0+0j A</current_BC>
				<current_CA>+0+0j A</current_CA>
				<current_AN>+0+0j A</current_AN>
				<current_BN>+0+0j A</current_BN>
				<current_CN>+0+0j A</current_CN>
				<power_AB>+0+0j VA</power_AB>
				<power_BC>+0+0j VA</power_BC>
				<power_CA>+0+0j VA</power_CA>
				<power_AN>+0+0j VA</power_AN>
				<power_BN>+0+0j VA</power_BN>
				<power_CN>+0+0j VA</power_CN>
				<shunt_AB>+0+0j S</shunt_AB>
				<shunt_BC>+0+0j S</shunt_BC>
				<shunt_CA>+0+0j S</shunt_CA>
				<shunt_AN>+0+0j S</shunt_AN>
				<shunt_BN>+0+0j S</shunt_BN>
				<shunt_CN>+0+0j S</shunt_CN>
				<mean_repair_time>+0 s</mean_repair_time>
				<frequency_measure_type>NONE</frequency_measure_type>
				<sfm_T>+0.01 s</sfm_T>
				<pll_Kp>+10 pu</pll_Kp>
				<pll_Ki>+100 pu</pll_Ki>
				<measured_angle_A>+0 rad</measured_angle_A>
				<measured_frequency_A>+60 Hz</measured_frequency_A>
				<measured_angle_B>+0 rad</measured_angle_B>
				<measured_frequency_B>+60 Hz</measured_frequency_B>
				<measured_angle_C>+0 rad</measured_angle_C>
				<measured_frequency_C>+60 Hz</measured_frequency_C>
				<measured_frequency>+60 Hz</measured_frequency>
				<service_status>IN_SERVICE</service_status>
				<service_status_double>-1</service_status_double>
				<previous_uptime>-1 min</previous_uptime>
				<current_uptime>+0.166667 min</current_uptime>
				<Norton_dynamic>FALSE</Norton_dynamic>
				<GFA_enable>FALSE</GFA_enable>
				<GFA_freq_low_trip>+59.5 Hz</GFA_freq_low_trip>
				<GFA_freq_high_trip>+60.5 Hz</GFA_freq_high_trip>
				<GFA_volt_low_trip>+0.8 pu</GFA_volt_low_trip>
				<GFA_volt_high_trip>+1.2 pu</GFA_volt_high_trip>
				<GFA_reconnect_time>+300 s</GFA_reconnect_time>
				<GFA_freq_disconnect_time>+0.2 s</GFA_freq_disconnect_time>
				<GFA_volt_disconnect_time>+0.2 s</GFA_volt_disconnect_time>
				<GFA_status>TRUE</GFA_status>
				<phases>ABCN</phases>
				<nominal_voltage>+2400 V</nominal_voltage>
			</meter>
		</meter_list>
		<line_list>
			<inherits_from>link</inherits_from>
		</line_list>
		<line_spacing_list>
		</line_spacing_list>
		<overhead_line_list>
			<inherits_from>line</inherits_from>
		</overhead_line_list>
		<underground_line_list>
			<inherits_from>line</inherits_from>
		</underground_line_list>
		<overhead_line_conductor_list>
		</overhead_line_conductor_list>
		<underground_line_conductor_list>
		</underground_line_conductor_list>
		<line_configuration_list>
		</line_configuration_list>
		<transformer_configuration_list>
		</transformer_configuration_list>
		<transformer_list>
			<inherits_from>link</inherits_from>
		</transformer_list>
		<load_list>
			<inherits_from>node</inherits_from>
		</load_list>
		<regulator_configuration_list>
		</regulator_configuration_list>
		<regulator_list>
			<inherits_from>link</inherits_from>
		</regulator_list>
		<triplex_node_list>
			<inherits_from>powerflow_object</inherits_from>
		</triplex_node_list>
		<triplex_meter_list>
			<inherits_from>triplex_node</inherits_from>
		</triplex_meter_list>
		<triplex_line_list>
			<inherits_from>line</inherits_from>
		</triplex_line_list>
		<triplex_line_configuration_list>
		</triplex_line_configuration_list>
		<triplex_line_conductor_list>
		</triplex_line_conductor_list>
		<switch_list>
			<inherits_from>link</inherits_from>
			<switch>
				<id>5</id>
				<rank>1</rank>
				<out_svc>NEVER</out_svc>
				<clock>2011-01-01 00:00:08 UTC</clock>
				<name>switch_1</name>
				<phase_A_state>CLOSED</phase_A_state>
				<phase_B_state>CLOSED</phase_B_state>
				<phase_C_state>CLOSED</phase_C_state>
				<operating_mode>BANKED</operating_mode>
				<switch_resistance>+0.0001 Ohm</switch_resistance>
				<status>CLOSED</status>
				<from>swing</from>
				<to>load_1</to>
				<power_in>-5.45697e-06+5.45697e-06i VA</power_in>
				<power_out>+7.71732e-06+135d VA</power_out>
				<power_out_real>-5.45697e-06 W</power_out_real>
				<power_losses>+4.23516e-22-4.23516e-22i VA</power_losses>
				<power_in_A>+0+0i VA</power_in_A>
				<power_in_B>+7.71732e-06+75d VA</power_in_B>
				<power_in_C>+7.71732e-06-165d VA</power_in_C>
				<power_out_A>+0+0d VA</power_out_A>
				<power_out_B>+7.71732e-06+75d VA</power_out_B>
				<power_out_C>+7.71732e-06-165d VA</power_out_C>
				<power_losses_A>+0+0i VA</power_losses_A>
				<power_losses_B>+4.23516e-22+0d VA</power_losses_B>
				<power_losses_C>+4.23516e-22-90d VA</power_losses_C>
				<current_out_A>+0+0j A</current_out_A>
				<current_out_B>+2.27374e-09+2.27374e-09j A</current_out_B>
				<current_out_C>+2.27374e-09+2.27374e-09j A</current_out_C>
				<current_in_A>+0+0i A</current_in_A>
				<current_in_B>+2.27374e-09+2.27374e-09i A</current_in_B>
				<current_in_C>+2.27374e-09+2.27374e-09i A</current_in_C>
				<fault_current_in_A>+0+0j A</fault_current_in_A>
				<fault_current_in_B>+0+0j A</fault_current_in_B>
				<fault_current_in_C>+0+0j A</fault_current_in_C>
				<fault_current_out_A>+0+0j A</fault_current_out_A>
				<fault_current_out_B>+0+0j A</fault_current_out_B>
				<fault_current_out_C>+0+0j A</fault_current_out_C>
				<flow_direction>CN|BN|AN</flow_direction>
				<mean_repair_time>+0 s</mean_repair_time>
				<continuous_rating>+1000 A</continuous_rating>
				<emergency_rating>+2000 A</emergency_rating>
				<inrush_convergence_value>+0.0001 V</inrush_convergence_value>
				<phases>ABCN</phases>
				<nominal_voltage>+2400 V</nominal_voltage>
			</switch>
			<switch>
				<id>7</id>
				<rank>1</rank>
				<out_svc>NEVER</out_svc>
				<clock>2011-01-01 00:00:08 UTC</clock>
				<name>switch_2</name>
				<phase_A_state>CLOSED</phase_A_state>
				<phase_B_state>CLOSED</phase_B_state>
				<phase_C_state>CLOSED</phase_C_state>
				<operating_mode>BANKED</operating_mode>
				<switch_resistance>+0.0001 Ohm</switch_resistance>
				<status>CLOSED</status>
				<from>swing</from>
				<to>load_2</to>
				<power_in>-5.45697e-06+5.45697e-06i VA</power_in>
				<power_out>+7.71732e-06+135d VA</power_out>
				<power_out_real>-5.45697e-06 W</power_out_real>
				<power_losses>+4.23516e-22-4.23516e-22i VA</power_losses>
				<power_in_A>+0+0i VA</power_in_A>
				<power_in_B>+7.71732e-06+75d VA</power_in_B>
				<power_in_C>+7.71732e-06-165d VA</power_in_C>
				<power_out_A>+0+0d VA</power_out_A>
				<power_out_B>+7.71732e-06+75d VA</power_out_B>
				<power_out_C>+7.71732e-06-165d VA</power_out_C>
				<power_losses_A>+0+0i VA</power_losses_A>
				<power_losses_B>+4.23516e-22+0d VA</power_losses_B>
				<power_losses_C>+4.23516e-22-90d VA</power_losses_C>
				<current_out_A>+0+0j A</current_out_A>
				<current_out_B>+2.27374e-09+2.27374e-09j A</current_out_B>
				<current_out_C>+2.27374e-09+2.27374e-09j A</current_out_C>
				<current_in_A>+0+0i A</current_in_A>
				<current_in_B>+2.27374e-09+2.27374e-09i A</current_in_B>
				<current_in_C>+2.27374e-09+2.27374e-09i A</current_in_C>
				<fault_current_in_A>+0+0j A</fault_current_in_A>
				<fault_current_in_B>+0+0j A</fault_current_in_B>
				<fault_current_in_C>+0+0j A</fault_current_in_C>
				<fault_current_out_A>+0+0j A</fault_current_out_A>
				<fault_current_out_B>+0+0j A</fault_current_out_B>
				<fault_current_out_C>+0+0j A</fault_current_out_C>
				<flow_direction>CN|BN|AN</flow_direction>
				<mean_repair_time>+0 s</mean_repair_time>
				<continuous_rating>+1000 A</continuous_rating>
				<emergency_rating>+2000 A</emergency_rating>
				<inrush_convergence_value>+0.0001 V</inrush_convergence_value>
				<phases>ABCN</phases>
				<nominal_voltage>+2400 V</nominal_voltage>
			</switch>
			<switch>
				<id>9</id>
				<rank>1</rank>
				<out_svc>NEVER</out_svc>
				<clock>2011-01-01 00:00:08 UTC</clock>
				<name>switch_3</name>
				<phase_A_state>CLOSED</phase_A_state>
				<phase_B_state>CLOSED</phase_B_state>
				<phase_C_state>CLOSED</phase_C_state>
				<operating_mode>BANKED</operating_mode>
				<switch_resistance>+0.0001 Ohm</switch_resistance>
				<status>CLOSED</status>
				<from>swing</from>
				<to>load_3</to>
				<power_in>+1.99739e-06+7.45436e-06i VA</power_in>
				<power_out>+7.71732e-06+75d VA</power_out>
				<power_out_real>+1.99739e-06 W</power_out_real>
				<power_losses>+4.23516e-22+0i VA</power_losses>
				<power_in_A>+0+0i VA</power_in_A>
				<power_in_B>+7.71732e-06+75d VA</power_in_B>
				<power_in_C>+0+0d VA</power_in_C>
				<power_out_A>+0+0d VA</power_out_A>
				<power_out_B>+7.71732e-06+75d VA</power_out_B>
				<power_out_C>+0+0d VA</power_out_C>
				<power_losses_A>+0+0i VA</power_losses_A>
				<power_losses_B>+4.23516e-22+0d VA</power_losses_B>
				<power_losses_C>+0+0d VA</power_losses_C>
				<current_out_A>+0+0j A</current_out_A>
				<current_out_B>+2.27374e-09+2.27374e-09j A</current_out_B>
				<current_out_C>+0+0j A</current_out_C>
				<current_in_A>+0+0i A</current_in_A>
				<current_in_B>+2.27374e-09+2.27374e-09i A</current_in_B>
				<current_in_C>+0+0i A</current_in_C>
				<fault_current_in_A>+0+0j A</fault_current_in_A>
				<fault_current_in_B>+0+0j A</fault_current_in_B>
				<fault_current_in_C>+0+0j A</fault_current_in_C>
				<fault_current_out_A>+0+0j A</fault_current_out_A>
				<fault_current_out_B>+0+0j A</fault_current_out_B>
				<fault_current_out_C>+0+0j A</fault_current_out_C>
				<flow_direction>CN|BN|AN</flow_direction>
				<mean_repair_time>+0 s</mean_repair_time>
				<continuous_rating>+1000 A</continuous_rating>
				<emergency_rating>+2000 A</emergency_rating>
				<inrush_convergence_value>+0.0001 V</inrush_convergence_value>
				<phases>ABCN</phases>
				<nominal_voltage>+2400 V</nominal_voltage>
			</switch>
			<switch>
				<id>11</id>
				<rank>1</rank>
				<out_svc>NEVER</out_svc>
				<clock>2011-01-01 00:00:08 UTC</clock>
				<name>switch_4</name>
				<phase_A_state>OPEN</phase_A_state>
				<phase_B_state>OPEN</phase_B_state>
				<phase_C_state>OPEN</phase_C_state>
				<operating_mode>BANKED</operating_mode>
				<switch_resistance>+0.0001 Ohm</switch_resistance>
				<status>OPEN</status>
				<from>swing</from>
				<to>load_4</to>
				<power_in>+1.99739e-06+7.45436e-06i VA</power_in>
				<power_out>+7.71732e-06+75d VA</power_out>
				<power_out_real>+1.99739e-06 W</power_out_real>
				<power_losses>+4.23516e-22+0i VA</power_losses>
				<power_in_A>+0+0i VA</power_in_A>
				<power_in_B>+7.71732e-06+75d VA</power_in_B>
				<power_in_C>+0+0d VA</power_in_C>
				<power_out_A>+0+0d VA</power_out_A>
				<power_out_B>+7.71732e-06+75d VA</power_out_B>
				<power_out_C>+0+0d VA</power_out_C>
				<power_losses_A>+0+0i VA</power_losses_A>
				<power_losses_B>+4.23516e-22+0d VA</power_losses_B>
				<power_losses_C>+0+0d VA</power_losses_C>
				<current_out_A>+0+0j A</current_out_A>
				<current_out_B>+2.27374e-09+2.27374e-09j A</current_out_B>
				<current_out_C>+0+0j A</current_out_C>
				<current_in_A>+0+0i A</current_in_A>
				<current_in_B>+2.27374e-09+2.27374e-09i A</current_in_B>
				<current_in_C>+0+0i A</current_in_C>
				<fault_current_in_A>+0+0j A</fault_current_in_A>
				<fault_current_in_B>+0+0j A</fault_current_in_B>
				<fault_current_in_C>+0+0j A</fault_current_in_C>
				<fault_current_out_A>+0+0j A</fault_current_out_A>
				<fault_current_out_B>+0+0j A</fault_current_out_B>
				<fault_current_out_C>+0+0j A</fault_current_out_C>
				<flow_direction>CN|BN|AN</flow_direction>
				<mean_repair_time>+0 s</mean_repair_time>
				<continuous_rating>+1000 A</continuous_rating>
				<emergency_rating>+2000 A</emergency_rating>
				<inrush_convergence_value>+0.0001 V</inrush_convergence_value>
				<phases>ABCN</phases>
				<nominal_voltage>+2400 V</nominal_voltage>
			</switch>
		</switch_list>
		<substation_list>
			<inherits_from>node</inherits_from>
		</substation_list>
		<pqload_list>
			<inherits_from>load</inherits_from>
		</pqload_list>
		<voltdump_list>
		</voltdump_list>
		<series_reactor_list>
			<inherits_from>link</inherits_from>
		</series_reactor_list>
		<restoration_list>
		</restoration_list>
		<frequency_gen_list>
		</frequency_gen_list>
		<volt_var_control_list>
		</volt_var_control_list>
		<fault_check_list>
		</fault_check_list>
		<motor_list>
			<inherits_from>node</inherits_from>
		</motor_list>
		<billdump_list>
		</billdump_list>
		<power_metrics_list>
		</power_metrics_list>
		<currdump_list>
		</currdump_list>
		<recloser_list>
			<inherits_from>switch</inherits_from>
		</recloser_list>
		<sectionalizer_list>
			<inherits_from>switch</inherits_from>
		</sectionalizer_list>
		<emissions_list>
		</emissions_list>
		<load_tracker_list>
		</load_tracker_list>
		<triplex_load_list>
			<inherits_from>triplex_node</inherits_from>
		</triplex_load_list>
		<impedance_dump_list>
		</impedance_dump_list>
	</powerflow>
	<tape>
		<version.major>4</version.major>
		<version.minor>0</version.minor>
		<player_list>
			<player>
				<id>14</id>
				<rank>0</rank>
				<out_svc>NEVER</out_svc>
				<parent>controller_1</parent>
				<clock>2011-01-01 00:00:10 UTC</clock>
				<name>player:14</name>
				<property>armed</property>
				<file>controller_1_armed.csv</file>
				<filetype>txt</filetype>
				<mode>file</mode>
				<loop>0</loop>
			</player>
			<player>
				<id>15</id>
				<rank>0</rank>
				<out_svc>NEVER</out_svc>
				<parent>controller_1</parent>
				<clock>2011-01-01 00:00:10 UTC</clock>
				<name>player:15</name>
				<property>status</property>
				<file>controller_1_status.csv</file>
				<filetype>txt</filetype>
				<mode>file</mode>
				<loop>0</loop>
			</player>
		</player_list>
		<shaper_list>
		</shaper_list>
		<recorder_list>
			<recorder>
				<id>6</id>
				<rank>0</rank>
				<out_svc>NEVER</out_svc>
				<parent>switch_1</parent>
				<clock>2011-01-01 00:00:08 UTC</clock>
				<name>recorder:6</name>
				<property>status</property>
				<trigger>""</trigger>
				<file>switch_1.csv</file>
				<filetype>txt</filetype>
				<mode>file</mode>
				<multifile>""</multifile>
				<limit>0</limit>
				<plotcommands>""</plotcommands>
				<xdata>""</xdata>
				<columns>""</columns>
				<flush>4294967295</flush>
				<interval>-1 s</interval>
				<output>SCREEN</output>
				<header_units>DEFAULT</header_units>
				<line_units>DEFAULT</line_units>
			</recorder>
			<recorder>
				<id>8</id>
				<rank>0</rank>
				<out_svc>NEVER</out_svc>
				<parent>switch_2</parent>
				<clock>2011-01-01 00:00:08 UTC</clock>
				<name>recorder:8</name>
				<property>status</property>
				<trigger>""</trigger>
				<file>switch_2.csv</file>
				<filetype>txt</filetype>
				<mode>file</mode>
				<multifile>""</multifile>
				<limit>0</limit>
				<plotcommands>""</plotcommands>
				<xdata>""</xdata>
				<columns>""</columns>
				<flush>4294967295</flush>
				<interval>-1 s</interval>
				<output>SCREEN</output>
				<header_units>DEFAULT</header_units>
				<line_units>DEFAULT</line_units>
			</recorder>
			<recorder>
				<id>10</id>
				<rank>0</rank>
				<out_svc>NEVER</out_svc>
				<parent>switch_3</parent>
				<clock>2011-01-01 00:00:08 UTC</clock>
				<name>recorder:10</name>
				<property>status</property>
				<trigger>""</trigger>
				<file>switch_3.csv</file>
				<filetype>txt</filetype>
				<mode>file</mode>
				<multifile>""</multifile>
				<limit>0</limit>
				<plotcommands>""</plotcommands>
				<xdata>""</xdata>
				<columns>""</columns>
				<flush>4294967295</flush>
				<interval>-1 s</interval>
				<output>SCREEN</output>
				<header_units>DEFAULT</header_units>
				<line_units>DEFAULT</line_units>
			</recorder>
			<recorder>
				<id>12</id>
				<rank>0</rank>
				<out_svc>NEVER</out_svc>
				<parent>switch_4</parent>
				<clock>2011-01-01 00:00:08 UTC</clock>
				<name>recorder:12</name>
				<property>status</property>
				<trigger>""</trigger>
				<file>switch_4.csv</file>
				<filetype>txt</filetype>
				<mode>file</mode>
				<multifile>""</multifile>
				<limit>0</limit>
				<plotcommands>""</plotcommands>
				<xdata>""</xdata>
				<columns>""</columns>
				<flush>4294967295</flush>
				<interval>-1 s</interval>
				<output>SCREEN</output>
				<header_units>DEFAULT</header_units>
				<line_units>DEFAULT</line_units>
			</recorder>
			<recorder>
				<id>16</id>
				<rank>0</rank>
				<out_svc>NEVER</out_svc>
				<parent>controller_1</parent>
				<clock>2011-01-01 00:00:08 UTC</clock>
				<name>recorder:16</name>
				<property>status,armed</property>
				<trigger>""</trigger>
				<file>controller_1.csv</file>
				<filetype>txt</filetype>
				<mode>file</mode>
				<multifile>""</multifile>
				<limit>0</limit>
				<plotcommands>""</plotcommands>
				<xdata>""</xdata>
				<columns>""</columns>
				<flush>4294967295</flush>
				<interval>-1 s</interval>
				<output>SCREEN</output>
				<header_units>DEFAULT</header_units>
				<line_units>DEFAULT</line_units>
			</recorder>
		</recorder_list>
		<multi_recorder_list>
		</multi_recorder_list>
		<collector_list>
		</collector_list>
		<histogram_list>
		</histogram_list>
		<group_recorder_list>
		</group_recorder_list>
		<violation_recorder_list>
		</violation_recorder_list>
	</tape>
	<gismo>
		<version.major>4</version.major>
		<version.minor>0</version.minor>
		<line_sensor_list>
		</line_sensor_list>
		<switch_coordinator_list>
			<switch_coordinator>
				<id>13</id>
				<rank>1</rank>
				<out_svc>NEVER</out_svc>
				<clock>2011-01-01 00:00:10 UTC</clock>
				<name>controller_1</name>
				<status>ACTIVE</status>
				<armed>switch_4</armed>
			</switch_coordinator>
		</switch_coordinator_list>
	</gismo>
</gridlabd>
